git_fat-0.4.0.data/purelib/git_fat/git_fat.py
git_fat-0.4.0.data/purelib/git_fat/__init__.py
git_fat-0.4.0.data/scripts/git-fat
git_fat-0.4.0.data/scripts/git-fat.bat
git_fat-0.4.0.data/scripts/git-fat_gawk.exe
git_fat-0.4.0.data/scripts/git-fat_rsync.exe
git_fat-0.4.0.data/scripts/git-fat_ssh.exe
git_fat-0.4.0.data/scripts/msys-1.0.dll
git_fat-0.4.0.data/scripts/msys-crypto-1.0.0.dll
git_fat-0.4.0.data/scripts/msys-iconv-2.dll
git_fat-0.4.0.data/scripts/msys-intl-8.dll
git_fat-0.4.0.data/scripts/msys-minires.dll
git_fat-0.4.0.data/scripts/msys-popt-0.dll
git_fat-0.4.0.data/scripts/msys-z.dll
git_fat-0.4.0.dist-info/DESCRIPTION.rst
git_fat-0.4.0.dist-info/entry_points.txt
git_fat-0.4.0.dist-info/METADATA
git_fat-0.4.0.dist-info/metadata.json
git_fat-0.4.0.dist-info/RECORD
git_fat-0.4.0.dist-info/top_level.txt
git_fat-0.4.0.dist-info/WHEEL
