Metadata-Version: 2.0
Name: git-fat
Version: 0.4.0
Summary: Manage large binary files with git
Home-page: https://github.com/cyaninc/git-fat
Author: Alan Braithwaite
Author-email: alan.braithwaite@cyaninc.com
License: BSD 2-Clause
Platform: UNKNOWN
